quickrun/__init__.py
quickrun/cli/__init__.py
quickrun/cli/aws.py
quickrun/cli/helpers.py
quickrun/cli/ssh.py
quickrun/helpers/__init__.py
quickrun/helpers/formatters.py
quickrun-0.0.8.dist-info/LICENSE.txt
quickrun-0.0.8.dist-info/METADATA
quickrun-0.0.8.dist-info/WHEEL
quickrun-0.0.8.dist-info/top_level.txt
quickrun-0.0.8.dist-info/RECORD
