Metadata-Version: 2.1
Name: quickrun
Version: 0.0.8
Summary: Easily run commands and gather info across multiple servers
Home-page: https://github.com/danstewart/quickrun
Author: Dan Stewart
Author-email: git@mail.danstewart.dev
License: GPLv3
Platform: UNKNOWN
Classifier: License :: OSI Approved :: GNU General Public License v3 (GPLv3)
Classifier: Programming Language :: Python :: 3
Classifier: Programming Language :: Python :: 3.8
Requires-Dist: jq
Requires-Dist: pexpect
Requires-Dist: rich
